{
  "data_info": {
    "total_files": 4,
    "loaded_files": 4,
    "total_records": 340315,
    "vehicles": 2,
    "errors": [],
    "columns": [
      "Tiempo",
      "Coordenadas",
      "Velocidad",
      "Ubicaci\u00f3n",
      "Sensor",
      "Ignici\u00f3n",
      "Bater\u00eda interna",
      "Bater\u00eda veh\u00edculo",
      "P\u00e1nico",
      "Calidad de se\u00f1al",
      "Network Jamming",
      "GNSS Jamming",
      "Tanque Izquierdo",
      "Tanque Derecho",
      "Tanque Total",
      "Accel X",
      "Accel Y",
      "Accel Z",
      "Altitud",
      "Driver",
      "Stationary_drain",
      "Vehicle_ID",
      "Source_File"
    ],
    "dtypes": {
      "Tiempo": "datetime64[ns]",
      "Coordenadas": "object",
      "Velocidad": "int64",
      "Ubicaci\u00f3n": "object",
      "Sensor": "object",
      "Ignici\u00f3n": "object",
      "Bater\u00eda interna": "object",
      "Bater\u00eda veh\u00edculo": "object",
      "P\u00e1nico": "object",
      "Calidad de se\u00f1al": "object",
      "Network Jamming": "object",
      "GNSS Jamming": "object",
      "Tanque Izquierdo": "object",
      "Tanque Derecho": "object",
      "Tanque Total": "object",
      "Accel X": "object",
      "Accel Y": "object",
      "Accel Z": "object",
      "Altitud": "object",
      "Driver": "object",
      "Stationary_drain": "int64",
      "Vehicle_ID": "object",
      "Source_File": "object"
    },
    "memory_usage_mb": 307.5885925292969,
    "date_range": {
      "start": "2024-11-01 00:43:54",
      "end": "2025-03-31 23:59:38"
    }
  },
  "cleaning_report": {
    "original_rows": 340315,
    "final_rows": 338646,
    "rows_removed": 1669,
    "removal_percentage": 0.4904279858366513
  },
  "feature_info": {
    "total_features": 138,
    "feature_names": [
      "Velocidad",
      "Network Jamming",
      "GNSS Jamming",
      "Tanque Total",
      "Stationary_drain",
      "Hour",
      "DayOfWeek",
      "Day",
      "Month",
      "IsWeekend",
      "Is_NightTime",
      "Hour_Sin",
      "Hour_Cos",
      "DayOfWeek_Sin",
      "DayOfWeek_Cos",
      "Day_Sin",
      "Day_Cos",
      "Month_Sin",
      "Month_Cos",
      "Time_Diff",
      "Fuel_Diff",
      "Fuel_Rate",
      "Is_Stationary",
      "Stationary_Duration",
      "Is_Refuel",
      "Time_Since_Refuel",
      "Is_Sudden_Drop",
      "Driver_Fuel_Diff_mean",
      "Driver_Fuel_Diff_std",
      "Driver_Fuel_Diff_min",
      "Driver_Fuel_Diff_max",
      "Driver_Fuel_Diff_<lambda_0>",
      "Driver_Velocidad_mean",
      "Driver_Velocidad_std",
      "Driver_Velocidad_max",
      "Driver_Stationary_Duration_mean",
      "Driver_Stationary_Duration_max",
      "Driver_Is_NightTime_mean",
      "Driver_Is_Stationary_mean",
      "Fuel_Deviation_From_Driver",
      "Speed_Deviation_From_Driver",
      "Location_Risk_Score",
      "Location_Frequency",
      "Is_Rare_Location",
      "Vehicle_Tanque Total_mean",
      "Vehicle_Tanque Total_std",
      "Vehicle_Fuel_Diff_mean",
      "Vehicle_Fuel_Diff_std",
      "Vehicle_Is_NightTime_mean",
      "Vehicle_Is_Stationary_mean",
      "Is_Unusual_Speed",
      "Is_Unusual_Stationary",
      "Unusual_Behavior_Count",
      "Has_Multiple_Unusual",
      "Behavioral_Risk_Score",
      "Tanque Total_Rolling_Mean_5",
      "Tanque Total_Rolling_Std_5",
      "Tanque Total_Rolling_Min_5",
      "Tanque Total_Rolling_Max_5",
      "Fuel_Diff_Rolling_Mean_5",
      "Fuel_Diff_Rolling_Std_5",
      "Fuel_Diff_Rolling_Min_5",
      "Fuel_Diff_Rolling_Max_5",
      "Fuel_Rate_Rolling_Mean_5",
      "Fuel_Rate_Rolling_Std_5",
      "Velocidad_Rolling_Mean_5",
      "Velocidad_Rolling_Std_5",
      "Fuel_EWMA_5",
      "Tanque Total_Rolling_Mean_10",
      "Tanque Total_Rolling_Std_10",
      "Tanque Total_Rolling_Min_10",
      "Tanque Total_Rolling_Max_10",
      "Fuel_Diff_Rolling_Mean_10",
      "Fuel_Diff_Rolling_Std_10",
      "Fuel_Diff_Rolling_Min_10",
      "Fuel_Diff_Rolling_Max_10",
      "Fuel_Rate_Rolling_Mean_10",
      "Fuel_Rate_Rolling_Std_10",
      "Velocidad_Rolling_Mean_10",
      "Velocidad_Rolling_Std_10",
      "Fuel_EWMA_10",
      "Tanque Total_Rolling_Mean_30",
      "Tanque Total_Rolling_Std_30",
      "Tanque Total_Rolling_Min_30",
      "Tanque Total_Rolling_Max_30",
      "Fuel_Diff_Rolling_Mean_30",
      "Fuel_Diff_Rolling_Std_30",
      "Fuel_Diff_Rolling_Min_30",
      "Fuel_Diff_Rolling_Max_30",
      "Fuel_Rate_Rolling_Mean_30",
      "Fuel_Rate_Rolling_Std_30",
      "Velocidad_Rolling_Mean_30",
      "Velocidad_Rolling_Std_30",
      "Fuel_EWMA_30",
      "Tanque Total_Lag_1",
      "Fuel_Diff_Lag_1",
      "Velocidad_Lag_1",
      "Tanque Total_Lag_2",
      "Fuel_Diff_Lag_2",
      "Velocidad_Lag_2",
      "Tanque Total_Lag_3",
      "Fuel_Diff_Lag_3",
      "Velocidad_Lag_3",
      "Fuel_Range_10",
      "Fuel_Range_30",
      "Tanque Total_CV_5",
      "Tanque Total_CV_10",
      "Tanque Total_CV_30",
      "Fuel_Rate_CV_5",
      "Fuel_Rate_CV_10",
      "Fuel_Rate_CV_30",
      "Fuel_MACD",
      "Tanque Total_ZScore",
      "Tanque Total_ZScore_Local",
      "Fuel_Diff_ZScore",
      "Fuel_Diff_ZScore_Local",
      "Fuel_Rate_ZScore",
      "Fuel_Rate_ZScore_Local",
      "Stationary_Duration_ZScore",
      "Stationary_Duration_ZScore_Local",
      "Tanque Total_HighZScore",
      "Fuel_Diff_HighZScore",
      "Fuel_Rate_HighZScore",
      "Stationary_Duration_HighZScore",
      "Fuel_Change_Magnitude",
      "Is_Large_Change",
      "Is_Extreme_Change",
      "Is_Fuel_Loss",
      "Consecutive_Losses",
      "Fuel_Acceleration",
      "Is_Sharp_Deceleration",
      "Anomaly_Score",
      "Anomaly_stationary_loss",
      "Anomaly_night_loss",
      "Anomaly_rapid_loss",
      "Anomaly_high_deviation",
      "Anomaly_sudden_drop",
      "Anomaly_unusual_location"
    ],
    "feature_metadata": {
      "temporal": [
        "Day_Cos",
        "DayOfWeek_Cos",
        "DayOfWeek",
        "Month_Sin",
        "Fuel_Rate",
        "Is_NightTime",
        "IsWeekend",
        "Stationary_Duration",
        "Time_Diff",
        "Is_Refuel",
        "Hour_Sin",
        "Day_Sin",
        "Fuel_Diff",
        "Month",
        "Is_Stationary",
        "TimeOfDay",
        "DayOfWeek_Sin",
        "Month_Cos",
        "Day",
        "Time_Diff_Category",
        "Time_Since_Refuel",
        "Is_Sudden_Drop",
        "Hour_Cos",
        "Hour"
      ],
      "behavioral": [
        "Unusual_Behavior_Count",
        "Is_Unusual_Stationary",
        "Vehicle_Is_Stationary_mean",
        "Driver_Stationary_Duration_mean",
        "Is_Rare_Location",
        "Driver_Velocidad_mean",
        "Location_Risk_Score",
        "Driver_Stationary_Duration_max",
        "Vehicle_Fuel_Diff_std",
        "Driver_Is_Stationary_mean",
        "Driver_Fuel_Diff_std",
        "Has_Multiple_Unusual",
        "Vehicle_Fuel_Diff_mean",
        "Is_Unusual_Speed",
        "Vehicle_Tanque Total_mean",
        "Vehicle_Tanque Total_std",
        "Driver_Fuel_Diff_mean",
        "Driver_Velocidad_std",
        "Location_Frequency",
        "Vehicle_Is_NightTime_mean",
        "Driver_Is_NightTime_mean",
        "Driver_Fuel_Diff_<lambda_0>",
        "Driver_Fuel_Diff_min",
        "Behavioral_Risk_Score",
        "Driver_Fuel_Diff_max",
        "Fuel_Deviation_From_Driver",
        "Speed_Deviation_From_Driver",
        "Driver_Velocidad_max"
      ],
      "statistical": [
        "Fuel_Rate_Rolling_Std_5",
        "Tanque Total_Rolling_Mean_5",
        "Tanque Total_Rolling_Std_10",
        "Fuel_Rate_CV_5",
        "Is_Extreme_Change",
        "Velocidad_Rolling_Mean_10",
        "Tanque Total_Rolling_Max_5",
        "Tanque Total_Lag_3",
        "Fuel_Diff_Rolling_Min_10",
        "Fuel_Diff_Rolling_Mean_5",
        "Fuel_EWMA_30",
        "Is_Large_Change",
        "Is_Sharp_Deceleration",
        "Fuel_Range_10",
        "Tanque Total_Rolling_Mean_30",
        "Tanque Total_Rolling_Min_10",
        "Fuel_Change_Magnitude",
        "Fuel_Diff_ZScore",
        "Tanque Total_CV_30",
        "Tanque Total_Rolling_Max_30",
        "Velocidad_Lag_2",
        "Fuel_Diff_Rolling_Std_10",
        "Tanque Total_Lag_2",
        "Tanque Total_Rolling_Min_30",
        "Tanque Total_HighZScore",
        "Fuel_Rate_Rolling_Mean_30",
        "Stationary_Duration_ZScore_Local",
        "Fuel_Diff_Lag_1",
        "Fuel_Rate_Rolling_Std_10",
        "Fuel_MACD",
        "Consecutive_Losses",
        "Fuel_Diff_Rolling_Mean_10",
        "Fuel_Rate_HighZScore",
        "Tanque Total_Rolling_Std_30",
        "Velocidad_Lag_1",
        "Stationary_Duration_ZScore",
        "Velocidad_Rolling_Std_5",
        "Tanque Total_Lag_1",
        "Fuel_Rate_CV_30",
        "Velocidad_Rolling_Mean_5",
        "Tanque Total_Rolling_Std_5",
        "Fuel_Diff_Rolling_Max_5",
        "Stationary_Duration_HighZScore",
        "Tanque Total_Rolling_Mean_10",
        "Fuel_Diff_Rolling_Max_30",
        "Fuel_EWMA_5",
        "Fuel_Diff_HighZScore",
        "Fuel_Diff_Lag_3",
        "Fuel_Diff_Rolling_Max_10",
        "Fuel_EWMA_10",
        "Fuel_Rate_ZScore_Local",
        "Fuel_Rate_Rolling_Mean_5",
        "Is_Fuel_Loss",
        "Tanque Total_Rolling_Max_10",
        "Tanque Total_Rolling_Min_5",
        "Velocidad_Rolling_Mean_30",
        "Fuel_Diff_ZScore_Local",
        "Fuel_Diff_Lag_2",
        "Tanque Total_CV_5",
        "Fuel_Diff_Rolling_Std_5",
        "Tanque Total_ZScore",
        "Fuel_Acceleration",
        "Velocidad_Rolling_Std_30",
        "Fuel_Diff_Rolling_Mean_30",
        "Fuel_Rate_CV_10",
        "Fuel_Rate_ZScore",
        "Velocidad_Rolling_Std_10",
        "Velocidad_Lag_3",
        "Fuel_Diff_Rolling_Min_5",
        "Tanque Total_CV_10",
        "Fuel_Rate_Rolling_Mean_10",
        "Fuel_Rate_Rolling_Std_30",
        "Fuel_Diff_Rolling_Std_30",
        "Tanque Total_ZScore_Local",
        "Fuel_Diff_Rolling_Min_30",
        "Fuel_Range_30"
      ],
      "anomaly": [
        "Anomaly_Score",
        "Anomaly_stationary_loss",
        "Anomaly_night_loss",
        "Anomaly_rapid_loss",
        "Anomaly_high_deviation",
        "Anomaly_sudden_drop",
        "Anomaly_unusual_location"
      ]
    }
  },
  "unsupervised": {
    "pca": {
      "n_components_90": "1",
      "explained_variance_ratio": "[9.99552488e-01 4.42438819e-04 4.33159679e-06 6.32805993e-07\n 5.48790749e-08 5.22284588e-08 1.14043847e-09 1.56574585e-10\n 4.77414885e-11 1.78886478e-11 1.65702296e-11 7.86568300e-12\n 6.30335527e-12 4.99797405e-12 4.80766348e-12 2.55558664e-12\n 2.17303574e-12 1.99018776e-12 1.85963575e-12 1.58735063e-12\n 1.24200099e-12 1.15888540e-12 1.07296532e-12 9.64820421e-13\n 8.55886101e-13 7.57909472e-13 6.73960397e-13 5.28972235e-13\n 4.70964494e-13 4.22924982e-13 3.61863933e-13 3.56347585e-13\n 2.92662864e-13 2.81402109e-13 2.68638973e-13 2.20813972e-13\n 2.07785366e-13 1.72788028e-13 1.53841468e-13 1.47175435e-13\n 1.37285013e-13 1.27521783e-13 1.25798746e-13 1.22185321e-13\n 1.16808706e-13 1.10175543e-13 9.26753082e-14 7.83714412e-14\n 7.43590976e-14 7.00965980e-14 6.36561302e-14 5.81755430e-14\n 5.58581541e-14 4.12654332e-14 3.84395119e-14 3.32759604e-14\n 3.29679240e-14 2.71431919e-14 2.60879309e-14 2.57136328e-14\n 2.33512946e-14 2.00740547e-14 1.71666523e-14 1.58675999e-14\n 1.40968860e-14 1.36453072e-14 1.25164383e-14 9.13293725e-15\n 9.04417794e-15 8.39701545e-15 8.33849678e-15 7.50179728e-15\n 6.32107416e-15 5.76932754e-15 5.38245907e-15 4.51476166e-15\n 3.93433359e-15 3.71138862e-15 2.99964895e-15 2.56144200e-15\n 2.19747973e-15 2.10784945e-15 2.06919390e-15 1.90594998e-15\n 1.08489440e-15 1.05769917e-15 6.64105309e-16 5.88117522e-16\n 2.44047031e-16 2.40372822e-16 2.30832877e-16 2.16986369e-16\n 1.49271407e-16 1.04153072e-16 8.71511364e-17 6.78532689e-17\n 5.75158106e-17 4.65002603e-17 3.81904726e-17 3.34008314e-17\n 1.82985838e-17 9.75586099e-18 2.81324985e-18 2.43446931e-18\n 1.91662480e-18 5.12132060e-19 3.83646964e-19 2.26524686e-19\n 2.17439430e-19 1.61957617e-19 2.42915272e-20 1.34632761e-20\n 2.03212230e-21 8.69012897e-22 1.57508329e-22 3.89810098e-23\n 3.55475791e-24 2.98950026e-26 4.89369296e-27 1.94532477e-27\n 3.41204498e-28 3.94346099e-29 2.67044385e-29 3.28455182e-30\n 0.00000000e+00 0.00000000e+00 0.00000000e+00 0.00000000e+00\n 0.00000000e+00 0.00000000e+00 0.00000000e+00 0.00000000e+00\n 0.00000000e+00 0.00000000e+00 0.00000000e+00 0.00000000e+00\n 0.00000000e+00 0.00000000e+00]",
      "cumulative_variance_ratio": "[0.99955249 0.99999493 0.99999926 0.99999989 0.99999995 1.\n 1.         1.         1.         1.         1.         1.\n 1.         1.         1.         1.         1.         1.\n 1.         1.         1.         1.         1.         1.\n 1.         1.         1.         1.         1.         1.\n 1.         1.         1.         1.         1.         1.\n 1.         1.         1.         1.         1.         1.\n 1.         1.         1.         1.         1.         1.\n 1.         1.         1.         1.         1.         1.\n 1.         1.         1.         1.         1.         1.\n 1.         1.         1.         1.         1.         1.\n 1.         1.         1.         1.         1.         1.\n 1.         1.         1.         1.         1.         1.\n 1.         1.         1.         1.         1.         1.\n 1.         1.         1.         1.         1.         1.\n 1.         1.         1.         1.         1.         1.\n 1.         1.         1.         1.         1.         1.\n 1.         1.         1.         1.         1.         1.\n 1.         1.         1.         1.         1.         1.\n 1.         1.         1.         1.         1.         1.\n 1.         1.         1.         1.         1.         1.\n 1.         1.         1.         1.         1.         1.\n 1.         1.         1.         1.         1.         1.        ]",
      "components": "[[-3.34789634e+04 -1.17756807e+03 -8.71181124e+01 ... -5.96503664e-04\n   5.86888527e-04  3.09541948e-02]\n [-3.35648696e+04 -1.17876553e+03 -8.77920321e+01 ... -5.70000371e-04\n   7.95015211e-04  3.39123336e-02]\n [-3.34984267e+04 -1.17810500e+03 -8.76368743e+01 ...  4.37279064e-04\n  -6.08727702e-04  1.25963817e-03]\n ...\n [-3.34374715e+04 -1.17404259e+03 -8.73725550e+01 ...  1.85354913e-05\n  -4.60922031e-06 -3.13831860e-03]\n [-3.34560001e+04 -1.17449582e+03 -8.74888993e+01 ...  2.43504209e-05\n  -1.10450763e-05 -3.68047096e-03]\n [-3.34125642e+04 -1.17748328e+03 -8.75144824e+01 ...  3.62313700e-05\n  -4.83541552e-05 -3.48444765e-03]]"
    },
    "kmeans": {
      "optimal_k": 2,
      "clusters": "[0 0 0 ... 0 0 0]",
      "suspicious_clusters": [],
      "cluster_sizes": {
        "0": 338630,
        "1": 16
      }
    },
    "dbscan": {
      "clusters": "[-1 -1 -1 ... -1 -1 -1]",
      "n_outliers": "328881",
      "outlier_rate": 0.9711645789408409,
      "n_clusters": 851
    },
    "isolation_forest": {
      "predictions": "[1 1 1 ... 1 1 1]",
      "scores": "[-0.4826271  -0.50184077 -0.51134556 ... -0.51299698 -0.52447234\n -0.52720336]",
      "n_anomalies": "3387",
      "anomaly_rate": 0.010001594585496359
    },
    "ensemble": {
      "threshold": 0.3125,
      "n_anomalies": "9542",
      "anomaly_rate": 0.02817691630788493
    },
    "n_anomalies": "9542",
    "anomaly_rate": 0.02817691630788493
  },
  "supervised": {
    "model_results": {
      "Logistic Regression": {
        "accuracy": 0.9979624981544367,
        "precision": 0.1320754716981132,
        "recall": 1.0,
        "f1": 0.23333333333333334,
        "roc_auc": 0.9999465499768265
      },
      "Random Forest": {
        "accuracy": 0.9999852354938727,
        "precision": 1.0,
        "recall": 0.9523809523809523,
        "f1": 0.975609756097561,
        "roc_auc": 1.0
      },
      "XGBoost": {
        "accuracy": 1.0,
        "precision": 1.0,
        "recall": 1.0,
        "f1": 1.0,
        "roc_auc": 1.0
      },
      "LightGBM": {
        "accuracy": 1.0,
        "precision": 1.0,
        "recall": 1.0,
        "f1": 1.0,
        "roc_auc": 1.0
      },
      "Neural Network": {
        "accuracy": 0.9996751808652,
        "precision": 0.4878048780487805,
        "recall": 0.9523809523809523,
        "f1": 0.6451612903225806,
        "roc_auc": 0.99992474799369
      }
    },
    "best_model": "XGBoost",
    "best_score": 1.0,
    "cv_results": {
      "accuracy": 1.0,
      "precision": 1.0,
      "recall": 1.0,
      "f1": 1.0
    },
    "feature_importance": "                             Random Forest  XGBoost  LightGBM  Mean_Importance\nVelocidad                         0.071667      0.0       185        61.690556\nNetwork Jamming                   0.000173      0.0       107        35.666724\nStationary_drain                  0.103580      1.0       100        33.701193\nTanque Total                      0.002875      0.0        92        30.667625\nHour                              0.000763      0.0        32        10.666921\n...                                    ...      ...       ...              ...\nIs_Refuel                         0.000000      0.0         0         0.000000\nIs_Rare_Location                  0.000000      0.0         0         0.000000\nDriver_Fuel_Diff_<lambda_0>       0.000000      0.0         0         0.000000\nTanque Total_HighZScore           0.000000      0.0         0         0.000000\nFuel_Rate_HighZScore              0.000000      0.0         0         0.000000\n\n[138 rows x 4 columns]",
    "predictions": "[0 0 0 ... 0 0 0]",
    "test_size": 67730,
    "train_size": 270916
  },
  "ensemble": {
    "weights_used": {
      "unsupervised_ensemble": 0.5,
      "supervised": 0.5
    },
    "predictions": {
      "conservative": {
        "threshold": 0.8,
        "n_predictions": "48",
        "prediction_rate": 0.00014174093300969154
      },
      "balanced": {
        "threshold": 0.6,
        "n_predictions": "103",
        "prediction_rate": 0.0003041524187499631
      },
      "aggressive": {
        "threshold": 0.4,
        "n_predictions": "224",
        "prediction_rate": 0.0006614576873785605
      }
    },
    "total_predictions": "103",
    "detection_rate": 0.0003041524187499631,
    "high_risk_count": 48,
    "driver_risk": {
      